otsec/__init__.py
otsec/cli.py
otsec/core/__init__.py
otsec/core/banner.py
otsec/core/discovery.py
otsec/core/shell.py
otsec/core/vuln_db.py
otsec/core/injectors/__init__.py
otsec/core/injectors/modbus.py
otsec/data/vulns.yaml
otsec-0.1.1.dist-info/licenses/LICENSE
otsec-0.1.1.dist-info/METADATA
otsec-0.1.1.dist-info/WHEEL
otsec-0.1.1.dist-info/entry_points.txt
otsec-0.1.1.dist-info/top_level.txt
otsec-0.1.1.dist-info/RECORD
