Metadata-Version: 2.4
Name: otsec
Version: 0.1.1
Summary: Offensive OT/IoT Security Toolkit
License: All Rights Reserved
Keywords: ot,iot,ics,modbus,security,pentesting,redteam,network-scanner,python,kali-linux
Requires-Python: >=3.10
License-File: LICENSE
Requires-Dist: click>=8.1
Requires-Dist: scapy>=2.5.0
Requires-Dist: pymodbus>=3.6.6
Requires-Dist: PyYAML>=6.0
Dynamic: license-file
